[
  {
    "ContainingType": "ProjectManagement.Api.Controllers.BoardController",
    "Method": "CreateBoardAsync",
    "RelativePath": "api/Board",
    "HttpMethod": "POST",
    "IsController": true,
    "Order": 0,
    "Parameters": [
      {
        "Name": "dto",
        "Type": "ProjectManagement.Application.DTOs.Board.CreateBoardDto",
        "IsRequired": true
      }
    ],
    "ReturnTypes": []
  },
  {
    "ContainingType": "ProjectManagement.Api.Controllers.BoardController",
    "Method": "GetBoardByIdAsync",
    "RelativePath": "api/Board/{id}",
    "HttpMethod": "GET",
    "IsController": true,
    "Order": 0,
    "Parameters": [
      {
        "Name": "id",
        "Type": "System.Int32",
        "IsRequired": true
      }
    ],
    "ReturnTypes": [
      {
        "Type": "ProjectManagement.Application.DTOs.Board.BoardDto",
        "MediaTypes": [
          "text/plain",
          "application/json",
          "text/json"
        ],
        "StatusCode": 200
      }
    ],
    "EndpointName": "GetBoardById"
  },
  {
    "ContainingType": "ProjectManagement.Api.Controllers.BoardController",
    "Method": "UpdateBoardAsync",
    "RelativePath": "api/Board/{id}",
    "HttpMethod": "PUT",
    "IsController": true,
    "Order": 0,
    "Parameters": [
      {
        "Name": "id",
        "Type": "System.Int32",
        "IsRequired": true
      },
      {
        "Name": "dto",
        "Type": "ProjectManagement.Application.DTOs.Board.UpdateBoardDto",
        "IsRequired": true
      }
    ],
    "ReturnTypes": []
  },
  {
    "ContainingType": "ProjectManagement.Api.Controllers.BoardController",
    "Method": "DeleteBoardAsync",
    "RelativePath": "api/Board/{id}",
    "HttpMethod": "DELETE",
    "IsController": true,
    "Order": 0,
    "Parameters": [
      {
        "Name": "id",
        "Type": "System.Int32",
        "IsRequired": true
      }
    ],
    "ReturnTypes": []
  },
  {
    "ContainingType": "ProjectManagement.Api.Controllers.BoardController",
    "Method": "GetAllBoardsAsync",
    "RelativePath": "api/Board/getall",
    "HttpMethod": "GET",
    "IsController": true,
    "Order": 0,
    "Parameters": [],
    "ReturnTypes": [
      {
        "Type": "System.Collections.Generic.IEnumerable\u00601[[ProjectManagement.Application.DTOs.Board.BoardDto, ProjectManagement.Application, Version=1.0.0.0, Culture=neutral, PublicKeyToken=null]]",
        "MediaTypes": [
          "text/plain",
          "application/json",
          "text/json"
        ],
        "StatusCode": 200
      }
    ]
  },
  {
    "ContainingType": "ProjectManagement.Api.Controllers.ColumnController",
    "Method": "GetAllColumnsForBoardAsync",
    "RelativePath": "api/boards/{boardId}/columns",
    "HttpMethod": "GET",
    "IsController": true,
    "Order": 0,
    "Parameters": [
      {
        "Name": "boardId",
        "Type": "System.Int32",
        "IsRequired": true
      }
    ],
    "ReturnTypes": [
      {
        "Type": "System.Collections.Generic.IEnumerable\u00601[[ProjectManagement.Application.DTOs.Column.ColumnDto, ProjectManagement.Application, Version=1.0.0.0, Culture=neutral, PublicKeyToken=null]]",
        "MediaTypes": [
          "text/plain",
          "application/json",
          "text/json"
        ],
        "StatusCode": 200
      },
      {
        "Type": "Microsoft.AspNetCore.Mvc.ProblemDetails",
        "MediaTypes": [
          "text/plain",
          "application/json",
          "text/json"
        ],
        "StatusCode": 404
      }
    ]
  },
  {
    "ContainingType": "ProjectManagement.Api.Controllers.ColumnController",
    "Method": "CreateColumnAsync",
    "RelativePath": "api/boards/{boardId}/columns",
    "HttpMethod": "POST",
    "IsController": true,
    "Order": 0,
    "Parameters": [
      {
        "Name": "boardId",
        "Type": "System.Int32",
        "IsRequired": true
      },
      {
        "Name": "createColumnDto",
        "Type": "ProjectManagement.Application.DTOs.Column.CreateColumnDto",
        "IsRequired": true
      }
    ],
    "ReturnTypes": [
      {
        "Type": "ProjectManagement.Application.DTOs.Column.ColumnDto",
        "MediaTypes": [
          "text/plain",
          "application/json",
          "text/json"
        ],
        "StatusCode": 201
      },
      {
        "Type": "Microsoft.AspNetCore.Mvc.ProblemDetails",
        "MediaTypes": [
          "text/plain",
          "application/json",
          "text/json"
        ],
        "StatusCode": 400
      },
      {
        "Type": "Microsoft.AspNetCore.Mvc.ProblemDetails",
        "MediaTypes": [
          "text/plain",
          "application/json",
          "text/json"
        ],
        "StatusCode": 404
      }
    ]
  },
  {
    "ContainingType": "ProjectManagement.Api.Controllers.ColumnController",
    "Method": "GetColumnByIdAsync",
    "RelativePath": "api/boards/{boardId}/columns/{columnId}",
    "HttpMethod": "GET",
    "IsController": true,
    "Order": 0,
    "Parameters": [
      {
        "Name": "boardId",
        "Type": "System.Int32",
        "IsRequired": true
      },
      {
        "Name": "columnId",
        "Type": "System.Int32",
        "IsRequired": true
      }
    ],
    "ReturnTypes": [
      {
        "Type": "ProjectManagement.Application.DTOs.Column.ColumnDto",
        "MediaTypes": [
          "text/plain",
          "application/json",
          "text/json"
        ],
        "StatusCode": 200
      },
      {
        "Type": "Microsoft.AspNetCore.Mvc.ProblemDetails",
        "MediaTypes": [
          "text/plain",
          "application/json",
          "text/json"
        ],
        "StatusCode": 404
      }
    ],
    "EndpointName": "GetColumnById"
  },
  {
    "ContainingType": "ProjectManagement.Api.Controllers.ColumnController",
    "Method": "DeleteColumnAsync",
    "RelativePath": "api/boards/{boardId}/columns/{columnId}",
    "HttpMethod": "DELETE",
    "IsController": true,
    "Order": 0,
    "Parameters": [
      {
        "Name": "boardId",
        "Type": "System.Int32",
        "IsRequired": true
      },
      {
        "Name": "columnId",
        "Type": "System.Int32",
        "IsRequired": true
      }
    ],
    "ReturnTypes": [
      {
        "Type": "System.Void",
        "MediaTypes": [],
        "StatusCode": 204
      },
      {
        "Type": "Microsoft.AspNetCore.Mvc.ProblemDetails",
        "MediaTypes": [
          "text/plain",
          "application/json",
          "text/json"
        ],
        "StatusCode": 404
      }
    ]
  },
  {
    "ContainingType": "ProjectManagement.Api.Controllers.ColumnController",
    "Method": "UpdateColumnAsync",
    "RelativePath": "api/boards/{boardId}/columns/{columnId}",
    "HttpMethod": "PUT",
    "IsController": true,
    "Order": 0,
    "Parameters": [
      {
        "Name": "boardId",
        "Type": "System.Int32",
        "IsRequired": true
      },
      {
        "Name": "columnId",
        "Type": "System.Int32",
        "IsRequired": true
      },
      {
        "Name": "updateColumnDto",
        "Type": "ProjectManagement.Application.DTOs.Column.UpdateColumnDto",
        "IsRequired": true
      }
    ],
    "ReturnTypes": [
      {
        "Type": "System.Void",
        "MediaTypes": [],
        "StatusCode": 204
      },
      {
        "Type": "Microsoft.AspNetCore.Mvc.ProblemDetails",
        "MediaTypes": [
          "text/plain",
          "application/json",
          "text/json"
        ],
        "StatusCode": 400
      },
      {
        "Type": "Microsoft.AspNetCore.Mvc.ProblemDetails",
        "MediaTypes": [
          "text/plain",
          "application/json",
          "text/json"
        ],
        "StatusCode": 404
      }
    ]
  },
  {
    "ContainingType": "ProjectManagement.Api.Controllers.ColumnController",
    "Method": "ReorderColumns",
    "RelativePath": "api/boards/{boardId}/columns/reorder",
    "HttpMethod": "PUT",
    "IsController": true,
    "Order": 0,
    "Parameters": [
      {
        "Name": "boardId",
        "Type": "System.Int32",
        "IsRequired": true
      },
      {
        "Name": "dto",
        "Type": "ProjectManagement.Application.DTOs.Column.ReorderColumnsDto",
        "IsRequired": true
      }
    ],
    "ReturnTypes": [
      {
        "Type": "System.Void",
        "MediaTypes": [],
        "StatusCode": 204
      },
      {
        "Type": "Microsoft.AspNetCore.Mvc.ProblemDetails",
        "MediaTypes": [
          "text/plain",
          "application/json",
          "text/json"
        ],
        "StatusCode": 400
      },
      {
        "Type": "Microsoft.AspNetCore.Mvc.ProblemDetails",
        "MediaTypes": [
          "text/plain",
          "application/json",
          "text/json"
        ],
        "StatusCode": 404
      }
    ]
  },
  {
    "ContainingType": "ProjectManagement.Api.Controllers.GroupController",
    "Method": "GetAllGroupsForBoardAsync",
    "RelativePath": "api/boards/{boardId}/groups",
    "HttpMethod": "GET",
    "IsController": true,
    "Order": 0,
    "Parameters": [
      {
        "Name": "boardId",
        "Type": "System.Int32",
        "IsRequired": true
      }
    ],
    "ReturnTypes": [
      {
        "Type": "System.Collections.Generic.IEnumerable\u00601[[ProjectManagement.Application.DTOs.Group.GroupDto, ProjectManagement.Application, Version=1.0.0.0, Culture=neutral, PublicKeyToken=null]]",
        "MediaTypes": [
          "text/plain",
          "application/json",
          "text/json"
        ],
        "StatusCode": 200
      },
      {
        "Type": "Microsoft.AspNetCore.Mvc.ProblemDetails",
        "MediaTypes": [
          "text/plain",
          "application/json",
          "text/json"
        ],
        "StatusCode": 404
      }
    ]
  },
  {
    "ContainingType": "ProjectManagement.Api.Controllers.GroupController",
    "Method": "CreateGroupAsync",
    "RelativePath": "api/boards/{boardId}/groups",
    "HttpMethod": "POST",
    "IsController": true,
    "Order": 0,
    "Parameters": [
      {
        "Name": "boardId",
        "Type": "System.Int32",
        "IsRequired": true
      },
      {
        "Name": "dto",
        "Type": "ProjectManagement.Application.DTOs.Group.CreateGroupDto",
        "IsRequired": true
      }
    ],
    "ReturnTypes": [
      {
        "Type": "ProjectManagement.Application.DTOs.Group.GroupDto",
        "MediaTypes": [
          "text/plain",
          "application/json",
          "text/json"
        ],
        "StatusCode": 201
      },
      {
        "Type": "Microsoft.AspNetCore.Mvc.ProblemDetails",
        "MediaTypes": [
          "text/plain",
          "application/json",
          "text/json"
        ],
        "StatusCode": 400
      },
      {
        "Type": "Microsoft.AspNetCore.Mvc.ProblemDetails",
        "MediaTypes": [
          "text/plain",
          "application/json",
          "text/json"
        ],
        "StatusCode": 404
      }
    ]
  },
  {
    "ContainingType": "ProjectManagement.Api.Controllers.GroupController",
    "Method": "GetGroupByIdAsync",
    "RelativePath": "api/boards/{boardId}/groups/{groupId}",
    "HttpMethod": "GET",
    "IsController": true,
    "Order": 0,
    "Parameters": [
      {
        "Name": "boardId",
        "Type": "System.Int32",
        "IsRequired": true
      },
      {
        "Name": "groupId",
        "Type": "System.Int32",
        "IsRequired": true
      }
    ],
    "ReturnTypes": [
      {
        "Type": "ProjectManagement.Application.DTOs.Group.GroupDto",
        "MediaTypes": [
          "text/plain",
          "application/json",
          "text/json"
        ],
        "StatusCode": 200
      },
      {
        "Type": "Microsoft.AspNetCore.Mvc.ProblemDetails",
        "MediaTypes": [
          "text/plain",
          "application/json",
          "text/json"
        ],
        "StatusCode": 404
      }
    ],
    "EndpointName": "GetGroupById"
  },
  {
    "ContainingType": "ProjectManagement.Api.Controllers.GroupController",
    "Method": "UpdateGroupAsync",
    "RelativePath": "api/boards/{boardId}/groups/{groupId}",
    "HttpMethod": "PUT",
    "IsController": true,
    "Order": 0,
    "Parameters": [
      {
        "Name": "boardId",
        "Type": "System.Int32",
        "IsRequired": true
      },
      {
        "Name": "groupId",
        "Type": "System.Int32",
        "IsRequired": true
      },
      {
        "Name": "dto",
        "Type": "ProjectManagement.Application.DTOs.Group.UpdateGroupDto",
        "IsRequired": true
      }
    ],
    "ReturnTypes": [
      {
        "Type": "System.Void",
        "MediaTypes": [],
        "StatusCode": 204
      },
      {
        "Type": "Microsoft.AspNetCore.Mvc.ProblemDetails",
        "MediaTypes": [
          "text/plain",
          "application/json",
          "text/json"
        ],
        "StatusCode": 400
      },
      {
        "Type": "Microsoft.AspNetCore.Mvc.ProblemDetails",
        "MediaTypes": [
          "text/plain",
          "application/json",
          "text/json"
        ],
        "StatusCode": 404
      }
    ]
  },
  {
    "ContainingType": "ProjectManagement.Api.Controllers.GroupController",
    "Method": "DeleteGroupAsync",
    "RelativePath": "api/boards/{boardId}/groups/{groupId}",
    "HttpMethod": "DELETE",
    "IsController": true,
    "Order": 0,
    "Parameters": [
      {
        "Name": "boardId",
        "Type": "System.Int32",
        "IsRequired": true
      },
      {
        "Name": "groupId",
        "Type": "System.Int32",
        "IsRequired": true
      }
    ],
    "ReturnTypes": [
      {
        "Type": "System.Void",
        "MediaTypes": [],
        "StatusCode": 204
      },
      {
        "Type": "Microsoft.AspNetCore.Mvc.ProblemDetails",
        "MediaTypes": [
          "text/plain",
          "application/json",
          "text/json"
        ],
        "StatusCode": 404
      }
    ]
  },
  {
    "ContainingType": "ProjectManagement.Api.Controllers.GroupController",
    "Method": "ReorderGroups",
    "RelativePath": "api/boards/{boardId}/groups/reorder",
    "HttpMethod": "PUT",
    "IsController": true,
    "Order": 0,
    "Parameters": [
      {
        "Name": "boardId",
        "Type": "System.Int32",
        "IsRequired": true
      },
      {
        "Name": "dto",
        "Type": "ProjectManagement.Application.DTOs.Group.ReorderGroupsDto",
        "IsRequired": true
      }
    ],
    "ReturnTypes": [
      {
        "Type": "System.Void",
        "MediaTypes": [],
        "StatusCode": 204
      },
      {
        "Type": "Microsoft.AspNetCore.Mvc.ProblemDetails",
        "MediaTypes": [
          "text/plain",
          "application/json",
          "text/json"
        ],
        "StatusCode": 400
      },
      {
        "Type": "Microsoft.AspNetCore.Mvc.ProblemDetails",
        "MediaTypes": [
          "text/plain",
          "application/json",
          "text/json"
        ],
        "StatusCode": 404
      }
    ]
  },
  {
    "ContainingType": "ProjectManagement.Api.Controllers.ItemController",
    "Method": "GetAllItemsAsync",
    "RelativePath": "api/boards/{boardId}/items",
    "HttpMethod": "GET",
    "IsController": true,
    "Order": 0,
    "Parameters": [
      {
        "Name": "boardId",
        "Type": "System.Int32",
        "IsRequired": true
      },
      {
        "Name": "groupId",
        "Type": "System.Nullable\u00601[[System.Int32, System.Private.CoreLib, Version=8.0.0.0, Culture=neutral, PublicKeyToken=7cec85d7bea7798e]]",
        "IsRequired": false
      }
    ],
    "ReturnTypes": [
      {
        "Type": "System.Collections.Generic.IEnumerable\u00601[[ProjectManagement.Application.DTOs.Item.ItemDto, ProjectManagement.Application, Version=1.0.0.0, Culture=neutral, PublicKeyToken=null]]",
        "MediaTypes": [
          "text/plain",
          "application/json",
          "text/json"
        ],
        "StatusCode": 200
      },
      {
        "Type": "Microsoft.AspNetCore.Mvc.ProblemDetails",
        "MediaTypes": [
          "text/plain",
          "application/json",
          "text/json"
        ],
        "StatusCode": 400
      },
      {
        "Type": "Microsoft.AspNetCore.Mvc.ProblemDetails",
        "MediaTypes": [
          "text/plain",
          "application/json",
          "text/json"
        ],
        "StatusCode": 404
      }
    ]
  },
  {
    "ContainingType": "ProjectManagement.Api.Controllers.ItemController",
    "Method": "CreateItemAsync",
    "RelativePath": "api/boards/{boardId}/items",
    "HttpMethod": "POST",
    "IsController": true,
    "Order": 0,
    "Parameters": [
      {
        "Name": "boardId",
        "Type": "System.Int32",
        "IsRequired": true
      },
      {
        "Name": "groupId",
        "Type": "System.Int32",
        "IsRequired": false
      },
      {
        "Name": "createItemDto",
        "Type": "ProjectManagement.Application.DTOs.Item.CreateItemDto",
        "IsRequired": true
      }
    ],
    "ReturnTypes": [
      {
        "Type": "ProjectManagement.Application.DTOs.Item.ItemDto",
        "MediaTypes": [
          "text/plain",
          "application/json",
          "text/json"
        ],
        "StatusCode": 201
      },
      {
        "Type": "Microsoft.AspNetCore.Mvc.ProblemDetails",
        "MediaTypes": [
          "text/plain",
          "application/json",
          "text/json"
        ],
        "StatusCode": 400
      },
      {
        "Type": "Microsoft.AspNetCore.Mvc.ProblemDetails",
        "MediaTypes": [
          "text/plain",
          "application/json",
          "text/json"
        ],
        "StatusCode": 404
      }
    ]
  },
  {
    "ContainingType": "ProjectManagement.Api.Controllers.ItemController",
    "Method": "GetItemByIdAsync",
    "RelativePath": "api/boards/{boardId}/items/{itemId}",
    "HttpMethod": "GET",
    "IsController": true,
    "Order": 0,
    "Parameters": [
      {
        "Name": "boardId",
        "Type": "System.Int32",
        "IsRequired": true
      },
      {
        "Name": "itemId",
        "Type": "System.Int32",
        "IsRequired": true
      }
    ],
    "ReturnTypes": [
      {
        "Type": "ProjectManagement.Application.DTOs.Item.ItemDto",
        "MediaTypes": [
          "text/plain",
          "application/json",
          "text/json"
        ],
        "StatusCode": 200
      },
      {
        "Type": "Microsoft.AspNetCore.Mvc.ProblemDetails",
        "MediaTypes": [
          "text/plain",
          "application/json",
          "text/json"
        ],
        "StatusCode": 404
      }
    ],
    "EndpointName": "GetItemById"
  },
  {
    "ContainingType": "ProjectManagement.Api.Controllers.ItemController",
    "Method": "UpdateItemAsync",
    "RelativePath": "api/boards/{boardId}/items/{itemId}",
    "HttpMethod": "PUT",
    "IsController": true,
    "Order": 0,
    "Parameters": [
      {
        "Name": "boardId",
        "Type": "System.Int32",
        "IsRequired": true
      },
      {
        "Name": "itemId",
        "Type": "System.Int32",
        "IsRequired": true
      },
      {
        "Name": "updateItemDto",
        "Type": "ProjectManagement.Application.DTOs.Item.UpdateItemDto",
        "IsRequired": true
      }
    ],
    "ReturnTypes": [
      {
        "Type": "System.Void",
        "MediaTypes": [],
        "StatusCode": 204
      },
      {
        "Type": "Microsoft.AspNetCore.Mvc.ProblemDetails",
        "MediaTypes": [
          "text/plain",
          "application/json",
          "text/json"
        ],
        "StatusCode": 400
      },
      {
        "Type": "Microsoft.AspNetCore.Mvc.ProblemDetails",
        "MediaTypes": [
          "text/plain",
          "application/json",
          "text/json"
        ],
        "StatusCode": 404
      }
    ]
  },
  {
    "ContainingType": "ProjectManagement.Api.Controllers.ItemController",
    "Method": "DeleteItemAsync",
    "RelativePath": "api/boards/{boardId}/items/{itemId}",
    "HttpMethod": "DELETE",
    "IsController": true,
    "Order": 0,
    "Parameters": [
      {
        "Name": "boardId",
        "Type": "System.Int32",
        "IsRequired": true
      },
      {
        "Name": "itemId",
        "Type": "System.Int32",
        "IsRequired": true
      }
    ],
    "ReturnTypes": [
      {
        "Type": "System.Void",
        "MediaTypes": [],
        "StatusCode": 204
      },
      {
        "Type": "Microsoft.AspNetCore.Mvc.ProblemDetails",
        "MediaTypes": [
          "text/plain",
          "application/json",
          "text/json"
        ],
        "StatusCode": 404
      }
    ]
  },
  {
    "ContainingType": "ProjectManagement.Api.Controllers.ItemController",
    "Method": "MoveItem",
    "RelativePath": "api/boards/{boardId}/items/move",
    "HttpMethod": "PUT",
    "IsController": true,
    "Order": 0,
    "Parameters": [
      {
        "Name": "boardId",
        "Type": "System.Int32",
        "IsRequired": true
      },
      {
        "Name": "dto",
        "Type": "ProjectManagement.Application.DTOs.Item.MoveItemDto",
        "IsRequired": true
      }
    ],
    "ReturnTypes": [
      {
        "Type": "System.Void",
        "MediaTypes": [],
        "StatusCode": 204
      },
      {
        "Type": "Microsoft.AspNetCore.Mvc.ProblemDetails",
        "MediaTypes": [
          "text/plain",
          "application/json",
          "text/json"
        ],
        "StatusCode": 400
      },
      {
        "Type": "Microsoft.AspNetCore.Mvc.ProblemDetails",
        "MediaTypes": [
          "text/plain",
          "application/json",
          "text/json"
        ],
        "StatusCode": 404
      }
    ]
  },
  {
    "ContainingType": "ProjectManagement.Api.Controllers.BoardViewsController",
    "Method": "GetBoardViews",
    "RelativePath": "api/boards/{boardId}/views",
    "HttpMethod": "GET",
    "IsController": true,
    "Order": 0,
    "Parameters": [
      {
        "Name": "boardId",
        "Type": "System.Int32",
        "IsRequired": true
      }
    ],
    "ReturnTypes": [
      {
        "Type": "System.Collections.Generic.IEnumerable\u00601[[ProjectManagement.Application.DTOs.BoardView.BoardViewDto, ProjectManagement.Application, Version=1.0.0.0, Culture=neutral, PublicKeyToken=null]]",
        "MediaTypes": [
          "text/plain",
          "application/json",
          "text/json"
        ],
        "StatusCode": 200
      }
    ]
  },
  {
    "ContainingType": "ProjectManagement.Api.Controllers.BoardViewsController",
    "Method": "CreateBoardView",
    "RelativePath": "api/boards/{boardId}/views",
    "HttpMethod": "POST",
    "IsController": true,
    "Order": 0,
    "Parameters": [
      {
        "Name": "boardId",
        "Type": "System.Int32",
        "IsRequired": true
      },
      {
        "Name": "createDto",
        "Type": "ProjectManagement.Application.DTOs.BoardView.CreateBoardViewDto",
        "IsRequired": true
      }
    ],
    "ReturnTypes": [
      {
        "Type": "ProjectManagement.Application.DTOs.BoardView.BoardViewDto",
        "MediaTypes": [
          "text/plain",
          "application/json",
          "text/json"
        ],
        "StatusCode": 200
      }
    ]
  },
  {
    "ContainingType": "ProjectManagement.Api.Controllers.BoardViewsController",
    "Method": "UpdateBoardView",
    "RelativePath": "api/boards/{boardId}/views/{viewId}",
    "HttpMethod": "PUT",
    "IsController": true,
    "Order": 0,
    "Parameters": [
      {
        "Name": "boardId",
        "Type": "System.Int32",
        "IsRequired": true
      },
      {
        "Name": "viewId",
        "Type": "System.Int32",
        "IsRequired": true
      },
      {
        "Name": "updateDto",
        "Type": "ProjectManagement.Application.DTOs.BoardView.UpdateBoardViewDto",
        "IsRequired": true
      }
    ],
    "ReturnTypes": []
  },
  {
    "ContainingType": "ProjectManagement.Api.Controllers.BoardViewsController",
    "Method": "DeleteBoardView",
    "RelativePath": "api/boards/{boardId}/views/{viewId}",
    "HttpMethod": "DELETE",
    "IsController": true,
    "Order": 0,
    "Parameters": [
      {
        "Name": "boardId",
        "Type": "System.Int32",
        "IsRequired": true
      },
      {
        "Name": "viewId",
        "Type": "System.Int32",
        "IsRequired": true
      }
    ],
    "ReturnTypes": []
  },
  {
    "ContainingType": "ProjectManagement.Api.Controllers.BoardViewsController",
    "Method": "ReorderBoardViews",
    "RelativePath": "api/boards/{boardId}/views/reorder",
    "HttpMethod": "PUT",
    "IsController": true,
    "Order": 0,
    "Parameters": [
      {
        "Name": "boardId",
        "Type": "System.Int32",
        "IsRequired": true
      },
      {
        "Name": "orderedViewIds",
        "Type": "System.Collections.Generic.List\u00601[[System.Int32, System.Private.CoreLib, Version=8.0.0.0, Culture=neutral, PublicKeyToken=7cec85d7bea7798e]]",
        "IsRequired": true
      }
    ],
    "ReturnTypes": []
  },
  {
    "ContainingType": "ProjectManagement.Api.Controllers.ItemValuesController",
    "Method": "UpsertItemValueAsync",
    "RelativePath": "api/items/{itemId}/values",
    "HttpMethod": "PUT",
    "IsController": true,
    "Order": 0,
    "Parameters": [
      {
        "Name": "itemId",
        "Type": "System.Int32",
        "IsRequired": true
      },
      {
        "Name": "dto",
        "Type": "ProjectManagement.Application.DTOs.ItemValue.UpdateItemValueDto",
        "IsRequired": true
      }
    ],
    "ReturnTypes": [
      {
        "Type": "ProjectManagement.Application.DTOs.ItemValue.ItemValueDto",
        "MediaTypes": [
          "text/plain",
          "application/json",
          "text/json"
        ],
        "StatusCode": 200
      }
    ]
  },
  {
    "ContainingType": "ProjectManagement.Api.Controllers.UserController",
    "Method": "GetAllUsersAsync",
    "RelativePath": "api/users",
    "HttpMethod": "GET",
    "IsController": true,
    "Order": 0,
    "Parameters": [],
    "ReturnTypes": [
      {
        "Type": "System.Collections.Generic.IEnumerable\u00601[[ProjectManagement.Application.DTOs.User.UserDto, ProjectManagement.Application, Version=1.0.0.0, Culture=neutral, PublicKeyToken=null]]",
        "MediaTypes": [
          "text/plain",
          "application/json",
          "text/json"
        ],
        "StatusCode": 200
      }
    ]
  },
  {
    "ContainingType": "ProjectManagement.Api.Controllers.UserController",
    "Method": "CreateUserAsync",
    "RelativePath": "api/users",
    "HttpMethod": "POST",
    "IsController": true,
    "Order": 0,
    "Parameters": [
      {
        "Name": "dto",
        "Type": "ProjectManagement.Application.DTOs.User.CreateUserDto",
        "IsRequired": true
      }
    ],
    "ReturnTypes": [
      {
        "Type": "ProjectManagement.Application.DTOs.User.UserDto",
        "MediaTypes": [
          "text/plain",
          "application/json",
          "text/json"
        ],
        "StatusCode": 201
      },
      {
        "Type": "Microsoft.AspNetCore.Mvc.ProblemDetails",
        "MediaTypes": [
          "text/plain",
          "application/json",
          "text/json"
        ],
        "StatusCode": 400
      }
    ]
  },
  {
    "ContainingType": "ProjectManagement.Api.Controllers.UserController",
    "Method": "GetUserByIdAsync",
    "RelativePath": "api/users/{userId}",
    "HttpMethod": "GET",
    "IsController": true,
    "Order": 0,
    "Parameters": [
      {
        "Name": "userId",
        "Type": "System.Int32",
        "IsRequired": true
      }
    ],
    "ReturnTypes": [
      {
        "Type": "ProjectManagement.Application.DTOs.User.UserDto",
        "MediaTypes": [
          "text/plain",
          "application/json",
          "text/json"
        ],
        "StatusCode": 200
      },
      {
        "Type": "Microsoft.AspNetCore.Mvc.ProblemDetails",
        "MediaTypes": [
          "text/plain",
          "application/json",
          "text/json"
        ],
        "StatusCode": 404
      }
    ],
    "EndpointName": "GetUserById"
  },
  {
    "ContainingType": "ProjectManagement.Api.Controllers.UserController",
    "Method": "UpdateUserAsync",
    "RelativePath": "api/users/{userId}",
    "HttpMethod": "PUT",
    "IsController": true,
    "Order": 0,
    "Parameters": [
      {
        "Name": "userId",
        "Type": "System.Int32",
        "IsRequired": true
      },
      {
        "Name": "dto",
        "Type": "ProjectManagement.Application.DTOs.User.UpdateUserDto",
        "IsRequired": true
      }
    ],
    "ReturnTypes": [
      {
        "Type": "System.Void",
        "MediaTypes": [],
        "StatusCode": 204
      },
      {
        "Type": "Microsoft.AspNetCore.Mvc.ProblemDetails",
        "MediaTypes": [
          "text/plain",
          "application/json",
          "text/json"
        ],
        "StatusCode": 400
      },
      {
        "Type": "Microsoft.AspNetCore.Mvc.ProblemDetails",
        "MediaTypes": [
          "text/plain",
          "application/json",
          "text/json"
        ],
        "StatusCode": 404
      }
    ]
  },
  {
    "ContainingType": "ProjectManagement.Api.Controllers.UserController",
    "Method": "DeleteUserAsync",
    "RelativePath": "api/users/{userId}",
    "HttpMethod": "DELETE",
    "IsController": true,
    "Order": 0,
    "Parameters": [
      {
        "Name": "userId",
        "Type": "System.Int32",
        "IsRequired": true
      }
    ],
    "ReturnTypes": [
      {
        "Type": "System.Void",
        "MediaTypes": [],
        "StatusCode": 204
      },
      {
        "Type": "Microsoft.AspNetCore.Mvc.ProblemDetails",
        "MediaTypes": [
          "text/plain",
          "application/json",
          "text/json"
        ],
        "StatusCode": 404
      }
    ]
  }
]